smpcp/__about__.py
smpcp/__init__.py
smpcp/smpcp.py
smpcp-2.0.2.dist-info/LICENSE
smpcp-2.0.2.dist-info/METADATA
smpcp-2.0.2.dist-info/WHEEL
smpcp-2.0.2.dist-info/top_level.txt
smpcp-2.0.2.dist-info/RECORD
