Metadata-Version: 2.1
Name: smpcp
Version: 2.0.2
Summary: Secure Multi-Party Computation Protocol base on Partially Homomorphic Encryption for Python
Home-page: https://github.com/shine813/Secure-Multi-Party-Computation-Protocol
Author: Zhan Shi
Author-email: phe.zshi@gmail.com
License: UNKNOWN
Platform: UNKNOWN
Classifier: Programming Language :: Python :: 3
Classifier: License :: OSI Approved :: MIT License
Classifier: Operating System :: OS Independent
